isitbullshit/core.py
isitbullshit/__init__.py
isitbullshit/structures.py
isitbullshit/exceptions.py
isitbullshit/testcase_mixin.py
isitbullshit-0.2.1.dist-info/top_level.txt
isitbullshit-0.2.1.dist-info/WHEEL
isitbullshit-0.2.1.dist-info/metadata.json
isitbullshit-0.2.1.dist-info/METADATA
isitbullshit-0.2.1.dist-info/RECORD
isitbullshit-0.2.1.dist-info/DESCRIPTION.rst
