Metadata-Version: 2.0
Name: isitbullshit
Version: 0.2.1
Summary: Small library for verifying parsed JSONs if they are bullshit or not
Home-page: https://github.com/9seconds/isitbullshit/
Author: Sergey Arkhipov
Author-email: serge@aerialsounds.org
License: MIT
Keywords: json validation jsonschema
Platform: UNKNOWN
Classifier: Development Status :: 4 - Beta
Classifier: Intended Audience :: Developers
Classifier: License :: OSI Approved :: MIT License
Classifier: Operating System :: OS Independent
Classifier: Programming Language :: Python :: 2.6
Classifier: Programming Language :: Python :: 2.7
Classifier: Programming Language :: Python :: 3.3
Classifier: Programming Language :: Python :: 3.4
Classifier: Programming Language :: Python :: 3.4
Classifier: Topic :: Software Development :: Libraries
Classifier: Topic :: Software Development :: Testing
Requires-Dist: six
